{
            "cristofer":{
                    "descricao": "esse monstro possui o poder de te hipnotizar",
                    "vida":"500", 
                    "demage":"100",
                    "opcoes": {
                            "fugir":"correr para as montanhas",
                            "enfrentar":"mostre para ele quem é que manda"
                            }
                        },
            "alanmo":{
                    "descricao": "esse monstro repete incessantemente que voce precisa prestar mais atenção na aula",
                    "vida":"750", 
                    "demage":"250",
                    "opcoes": {
                            "fugir":"correr para as montanhas",
                            "enfrentar":"mostre para ele quem é que manda"
                            }
                    }
            }
